.gitignore
README.md
requirements.txt
setup.py
test.sh
ox/__init__.py
ox/api.py
ox/cache.py
ox/file.py
ox/fixunicode.py
ox/format.py
ox/geo.py
ox/html.py
ox/image.py
ox/iso.py
ox/js.py
ox/jsonc.py
ox/location.py
ox/movie.py
ox/net.py
ox/normalize.py
ox/oembed.py
ox/srt.py
ox/text.py
ox/utils.py
ox/vtt.py
ox.egg-info/PKG-INFO
ox.egg-info/SOURCES.txt
ox.egg-info/dependency_links.txt
ox.egg-info/requires.txt
ox.egg-info/top_level.txt
ox/torrent/__init__.py
ox/torrent/bencode3.py
ox/torrent/makemetafile.py
ox/web/__init__.py
ox/web/abebooks.py
ox/web/allmovie.py
ox/web/amazon.py
ox/web/apple.py
ox/web/archive.py
ox/web/arsenalberlin.py
ox/web/auth.py
ox/web/criterion.py
ox/web/dailymotion.py
ox/web/duckduckgo.py
ox/web/epguides.py
ox/web/filmsdivision.py
ox/web/flixter.py
ox/web/freebase.py
ox/web/google.py
ox/web/imdb.py
ox/web/impawards.py
ox/web/itunes.py
ox/web/lookupbyisbn.py
ox/web/lyricsfly.py
ox/web/metacritic.py
ox/web/movieposterdb.py
ox/web/opensubtitles.py
ox/web/oxdb.py
ox/web/piratecinema.py
ox/web/rottentomatoes.py
ox/web/siteparser.py
ox/web/spiegel.py
ox/web/startpage.py
ox/web/thepiratebay.py
ox/web/tv.py
ox/web/twitter.py
ox/web/ubu.py
ox/web/vimeo.py
ox/web/wikipedia.py
ox/web/youtube.py